devtime/__init__.py
devtime/cli.py
devtime/database.py
devtime/service.py
devtime_cli-0.1.0.dist-info/METADATA
devtime_cli-0.1.0.dist-info/WHEEL
devtime_cli-0.1.0.dist-info/entry_points.txt
devtime_cli-0.1.0.dist-info/top_level.txt
devtime_cli-0.1.0.dist-info/RECORD
