Metadata-Version: 2.4
Name: devtime-cli
Version: 0.1.0
Summary: Minimal CLI tool to track development time
Author-email: Kais Sraieb <your-email@example.com>
License-Expression: MIT
Keywords: cli,productivity,time-tracking
Classifier: Programming Language :: Python :: 3
Classifier: Environment :: Console
Requires-Python: >=3.8
Requires-Dist: typer
